Code/Ass7/part2/part_a/not_gate.v
`timescale 1ns/1ps

module not_gate(input in, output out);

assign out= ~in;

endmodule

Code/Ass7/part2/part_b/flip_flop.v
`timescale 1ns/1ps

module flip_flop(input clk, input D, input reset, output reg Q);

always @(posedge clk, posedge reset)begin

	if(reset) Q<=0;

	else Q<=D;

end

endmodule

Code/Ass7/part2/part_a/and_gate.v
`timescale 1ns/1ps

module and_gate(input a, input b, output out);


assign out= a && b;

endmodule

Code/Ass7/part2/part_b/top1.v
`include "flip_flop.v"
`include "not_gate.v"
`include "and_gate.v"
`timescale 1ns/1ps


module top1(input in1, input in2, input clk, input reset, output out);

wire q11; wire q12; wire q13;
wire q21; wire q22; wire q23;
wire q1; wire q2;
wire q_not;  wire q_and;

flip_flop ff1(clk, in1, reset, q11);
flip_flop ff2(clk, q11, reset, q12);
flip_flop ff3(clk, q12, reset, q13);

//not_gate ng1(q13, q_not);

assign q_not=1;

flip_flop ff4(clk, in2, reset, q21);
flip_flop ff5(clk, q21, reset, q22);
flip_flop ff6(clk, q22, reset, q23);


and_gate ag1(q_not, q23, q_and);


flip_flop ff7(clk, q_and, reset, q1);
flip_flop ff8(clk, q1, reset, q2);
flip_flop ff9(clk, q2, reset, out);


endmodule

Code/Ass7/part2/part_b/top1_tb.v
`include "top1.v"

module top1_tb();

reg in1; reg in2; reg clk; reg reset;

wire out;


top1 uut(in1, in2, clk, reset, out);


initial begin
reset=1;
clk=0;
in1=0;
in2=0;
end

always begin
	#5;
	clk= ~clk;
	
end



initial begin

	$dumpfile("top1vcd.vcd");
	$dumpvars(0, top1_tb);
	reset=1;
	#2;

	reset=0;
	in1=1;
	in2=1;
	#100;

	$finish;

end

endmodule

Code/Ass7/part2/part_b/top1vcd.vcd
$date
	Thu Apr 21 22:31:50 2022
$end
$version
	Icarus Verilog
$end
$timescale
	1ps
$end
$scope module top1_tb $end
$var wire 1 ! out $end
$var reg 1 " clk $end
$var reg 1 # in1 $end
$var reg 1 $ in2 $end
$var reg 1 % reset $end
$scope module uut $end
$var wire 1 " clk $end
$var wire 1 # in1 $end
$var wire 1 $ in2 $end
$var wire 1 & q_not $end
$var wire 1 % reset $end
$var wire 1 ' q_and $end
$var wire 1 ( q23 $end
$var wire 1 ) q22 $end
$var wire 1 * q21 $end
$var wire 1 + q2 $end
$var wire 1 , q13 $end
$var wire 1 - q12 $end
$var wire 1 . q11 $end
$var wire 1 / q1 $end
$var wire 1 ! out $end
$scope module ag1 $end
$var wire 1 & a $end
$var wire 1 ' out $end
$var wire 1 ( b $end
$upscope $end
$scope module ff1 $end
$var wire 1 # D $end
$var wire 1 " clk $end
$var wire 1 % reset $end
$var reg 1 . Q $end
$upscope $end
$scope module ff2 $end
$var wire 1 . D $end
$var wire 1 " clk $end
$var wire 1 % reset $end
$var reg 1 - Q $end
$upscope $end
$scope module ff3 $end
$var wire 1 - D $end
$var wire 1 " clk $end
$var wire 1 % reset $end
$var reg 1 , Q $end
$upscope $end
$scope module ff4 $end
$var wire 1 $ D $end
$var wire 1 " clk $end
$var wire 1 % reset $end
$var reg 1 * Q $end
$upscope $end
$scope module ff5 $end
$var wire 1 * D $end
$var wire 1 " clk $end
$var wire 1 % reset $end
$var reg 1 ) Q $end
$upscope $end
$scope module ff6 $end
$var wire 1 ) D $end
$var wire 1 " clk $end
$var wire 1 % reset $end
$var reg 1 ( Q $end
$upscope $end
$scope module ff7 $end
$var wire 1 ' D $end
$var wire 1 " clk $end
$var wire 1 % reset $end
$var reg 1 / Q $end
$upscope $end
$scope module ff8 $end
$var wire 1 / D $end
$var wire 1 " clk $end
$var wire 1 % reset $end
$var reg 1 + Q $end
$upscope $end
$scope module ff9 $end
$var wire 1 + D $end
$var wire 1 " clk $end
$var wire 1 % reset $end
$var reg 1 ! Q $end
$upscope $end
$upscope $end
$upscope $end
$enddefinitions $end
#0
$dumpvars
0/
0.
0-
0,
0+
0*
0)
0(
0'
1&
1%
0$
0#
0"
0!
$end
#2000
1$
1#
0%
#5000
1*
1.
1"
#10000
0"
#15000
1-
1)
1"
#20000
0"
#25000
1'
1(
1,
1"
#30000
0"
#35000
1/
1"
#40000
0"
#45000
1+
1"
#50000
0"
#55000
1!
1"
