Code/Ass3/Q3/vdfsm.v
`timescale 1ns/1ps

module vdfsm(input clk,input reset, input L, input R, output speed_0,
	     output speed_1 ,output speed_2 ,output speed_3);

parameter S0=2'b00, S1=2'b01, S2= 2'b10, S3= 2'b11 ;
reg [1:0]state; reg [1:0]next_state;



always @(*)begin

	case(state)
		S0:begin if(L)next_state=S3; else if(R) next_state=S1; else next_state= state; end
		S1:begin if(L)next_state=S0; else if(R) next_state=S2; else next_state= state; end
		S2:begin if(L)next_state=S1; else if(R) next_state=S3; else next_state= state; end
		S3:begin if(L)next_state=S2; else if(R) next_state=S0; else next_state= state; end
	endcase
	
end

	



always @(posedge clk, posedge reset)begin

	if(reset)state<=S0;

	else state<= next_state;
end


assign speed_0= (state==S0)?1:0;
assign speed_1= (state==S1)?1:0;
assign speed_2= (state==S2)?1:0;
assign speed_3= (state==S3)?1:0;


endmodule

Code/Ass3/Q3/vdfsm_tb.v
//`include "vdfsm.v"
`timescale 1ns/1ps


module vdfsm_tb();

wire speed_0; wire speed_1; wire speed_2; wire speed_3;

reg L,R,clk,reset;

vdfsm uut(clk, reset, L, R, speed_0, speed_1, speed_2, speed_3);

initial begin
	clk=0;
	reset=1;
	L=0;
	R=0;
	#5;
end

always begin
	clk= ~clk;
	#5;
end


initial begin

	$dumpfile("vdfsm_vcd.vcd");
	$dumpvars(0, vdfsm_tb);

	reset=1;
	#2;
	reset=0;
	#2;

	L=1;	#10;

	L=0;	R=1;	#10;

	R=1;	#10;

	R=1;	#10;

	R=0;	L=1;	#10;

	L=1;	#10;

	L=1;	#10;

	$finish;
end

endmodule

Code/Ass3/Q3/vdfsm_vcd.vcd
$date
	Fri Feb 18 01:44:00 2022
$end
$version
	Icarus Verilog
$end
$timescale
	1ps
$end
$scope module vdfsm_tb $end
$var wire 1 ! speed_3 $end
$var wire 1 " speed_2 $end
$var wire 1 # speed_1 $end
$var wire 1 $ speed_0 $end
$var reg 1 % L $end
$var reg 1 & R $end
$var reg 1 ' clk $end
$var reg 1 ( reset $end
$scope module uut $end
$var wire 1 % L $end
$var wire 1 & R $end
$var wire 1 ' clk $end
$var wire 1 ( reset $end
$var wire 1 ! speed_3 $end
$var wire 1 " speed_2 $end
$var wire 1 # speed_1 $end
$var wire 1 $ speed_0 $end
$var reg 2 ) next_state [1:0] $end
$var reg 2 * state [1:0] $end
$upscope $end
$upscope $end
$enddefinitions $end
#0
$dumpvars
b0 *
b0 )
1(
1'
0&
0%
1$
0#
0"
0!
$end
#2000
0(
#4000
b11 )
1%
#5000
0'
#10000
0$
1!
b10 )
b11 *
1'
#14000
b0 )
1&
0%
#15000
0'
#20000
1$
0!
b1 )
b0 *
1'
#25000
0'
#30000
0$
1#
b10 )
b1 *
1'
#35000
0'
#40000
0#
1"
b11 )
b10 *
1'
#44000
b1 )
1%
0&
#45000
0'
#50000
1#
0"
b0 )
b1 *
1'
#55000
0'
#60000
1$
0#
b11 )
b0 *
1'
#65000
0'
#70000
0$
1!
b10 )
b11 *
1'
