Codes/Ass3/Q3/comb/vdfsm.v
`timescale 1ns/1ps

module vdfsm(input clk,input reset, input [1:0]LR, output [3:0]speed);

parameter S0=2'b00, S1=2'b01, S2= 2'b10, S3= 2'b11 ;
reg [1:0]state; reg [1:0]next_state;



always @(*)begin

	case(state)
		S0:begin if(LR==2'b10)next_state=S3; else if(LR==2'b01) next_state=S1; else next_state= state; end
		S1:begin if(LR==2'b10)next_state=S0; else if(LR==2'b01) next_state=S2; else next_state= state; end
		S2:begin if(LR==2'b10)next_state=S1; else if(LR==2'b01) next_state=S3; else next_state= state; end
		S3:begin if(LR==2'b10)next_state=S2; else if(LR==2'b01) next_state=S0; else next_state= state; end
	endcase
	
end

	



always @(posedge clk, posedge reset)begin

	if(reset)state<=S0;

	else state<= next_state;
end


assign speed[3]= (state==S0)?1:0;
assign speed[2]= (state==S1)?1:0;
assign speed[1]= (state==S2)?1:0;
assign speed[0]= (state==S3)?1:0;


endmodule

Code/Ass3/Q3/comb/vdfsm_tb.v
//`include "vdfsm.v"
`timescale 1ns/1ps


module vdfsm_tb();

wire [3:0]speed;

reg [1:0]LR;
reg clk,reset;

vdfsm uut(clk, reset, LR, speed);

initial begin
	clk=0;
	reset=1;
	LR=0;
	#5;
end


always begin
	clk= ~clk;
	#5;
end


initial begin

	$dumpfile("vdfsm_vcd.vcd");
	$dumpvars(0, vdfsm_tb);

	reset=1; #2;
	reset=0; #2;

	LR=1;	#10;
	LR=1;	#10;
	LR=1;	#10;
	LR=1;	#10;
	LR=2;	#10;
	LR=2;	#10;
	LR=1;	#10;
	LR=2;	#10;
	LR=1;	#10;
	LR=1;   #10;
	LR=1;	#10
	LR=2;	#10;

	$finish;
end

endmodule

Code/Ass3/Q3/comb/vdfsm_vcd.vcd
$date
	Fri Feb 18 17:04:32 2022
$end
$version
	Icarus Verilog
$end
$timescale
	1ps
$end
$scope module vdfsm_tb $end
$var wire 4 ! speed [3:0] $end
$var reg 2 " LR [1:0] $end
$var reg 1 # clk $end
$var reg 1 $ reset $end
$scope module uut $end
$var wire 2 % LR [1:0] $end
$var wire 1 # clk $end
$var wire 1 $ reset $end
$var wire 4 & speed [3:0] $end
$var reg 2 ' next_state [1:0] $end
$var reg 2 ( state [1:0] $end
$upscope $end
$upscope $end
$enddefinitions $end
#0
$dumpvars
b0 (
b0 '
b1000 &
b0 %
1$
1#
b0 "
b1000 !
$end
#2000
0$
#4000
b1 '
b1 "
b1 %
#5000
0#
#10000
b100 !
b100 &
b10 '
b1 (
1#
#15000
0#
#20000
b10 !
b10 &
b11 '
b10 (
1#
#25000
0#
#30000
b1 !
b1 &
b0 '
b11 (
1#
#35000
0#
#40000
b1000 !
b1000 &
b1 '
b0 (
1#
#44000
b11 '
b10 "
b10 %
#45000
0#
#50000
b1 !
b1 &
b10 '
b11 (
1#
#55000
0#
#60000
b10 !
b10 &
b1 '
b10 (
1#
#64000
b11 '
b1 "
b1 %
#65000
0#
#70000
b1 !
b1 &
b0 '
b11 (
1#
#74000
b10 '
b10 "
b10 %
#75000
0#
#80000
b10 !
b10 &
b1 '
b10 (
1#
#84000
b11 '
b1 "
b1 %
#85000
0#
#90000
b1 !
b1 &
b0 '
b11 (
1#
#95000
0#
#100000
b1000 !
b1000 &
b1 '
b0 (
1#
#105000
0#
#110000
b100 !
b100 &
b10 '
b1 (
1#
#114000
b0 '
b10 "
b10 %
#115000
0#
#120000
b1000 !
b1000 &
b11 '
b0 (
1#
